setup.py
Flask_Landing.egg-info/PKG-INFO
Flask_Landing.egg-info/SOURCES.txt
Flask_Landing.egg-info/dependency_links.txt
Flask_Landing.egg-info/requires.txt
Flask_Landing.egg-info/top_level.txt
app/__init__.py