Metadata-Version: 1.1
Name: Flask-Landing
Version: 0.1.0
Summary: Landing page for collecting emails.
Home-page: https://github.com/mjhea0/Flask-Landing
Author: Michael Herman
Author-email: michael@mherman.org
License: Apache Software License
Platform: any
Classifier: Programming Language :: Python
Classifier: Natural Language :: English
Classifier: Environment :: Web Environment
Classifier: Intended Audience :: Developers
Classifier: License :: OSI Approved :: Apache Software License
Classifier: Operating System :: OS Independent
Classifier: Topic :: Software Development :: Libraries :: Python Modules
Classifier: Topic :: Software Development :: Libraries :: Application Frameworks
Classifier: Topic :: Internet :: WWW/HTTP :: Dynamic Content
